blink.v
module blink;
  reg clk = 0;
  reg [3:0] count = 0;

  always #5 clk = ~clk;
  always @(posedge clk) count <= count + 1;
  always @(posedge clk) $display("time=%0t count=%0d", $time, count);

  initial begin
    $dumpfile("blink.vcd");
    $dumpvars(0, blink);
    #100 $finish;
  end
endmodule

blink.vcd
$date
	Tue Jun  2 12:00:01 2026
$end
$version
	Icarus Verilog
$end
$timescale
	1s
$end
$scope module blink $end
$var reg 1 ! clk $end
$var reg 4 " count [3:0] $end
$upscope $end
$enddefinitions $end
$comment Show the parameter values. $end
$dumpall
$end
#0
$dumpvars
b0 "
0!
$end
#5
b1 "
1!
#10
0!
#15
b10 "
1!
#20
0!
#25
b11 "
1!
#30
0!
#35
b100 "
1!
#40
0!
#45
b101 "
1!
#50
0!
#55
b110 "
1!
#60
0!
#65
b111 "
1!
#70
0!
#75
b1000 "
1!
#80
0!
#85
b1001 "
1!
#90
0!
#95
b1010 "
1!
